{
  "Content": {
    "0-Hand-Storage": {
      "宮西ひかる.jpg": "宮西ひかる.jpg?t=1736620634",
      "神宮寺ナオ.jpg": "神宮寺ナオ.jpg?t=1736620634",
      "倉田江里子.jpg": "倉田江里子.jpg?t=1736620634",
      "中山陽菜.jpg": "中山陽菜.jpg?t=1736620634",
      "あやみ旬果.jpg": "あやみ旬果.jpg?t=1736620634",
      "安みなみ.jpg": "安みなみ.jpg?t=1736620634",
      "羽咲みはる.jpg": "羽咲みはる.jpg?t=1736620634",
      "ジューン・ラブジョイ.jpg": "ジューン・ラブジョイ.jpg?t=1736620634",
      "鈴村あいり.jpg": "鈴村あいり.jpg?t=1736620634",
      "西宮ゆめ.jpg": "西宮ゆめ.jpg?t=1736620634",
      "京本かえで.jpg": "京本かえで.jpg?t=1736620634",
      "逢見リカ.jpg": "逢見リカ.jpg?t=1736620634",
      "桜空もも.jpg": "桜空もも.jpg?t=1736620634",
      "夏目響.jpg": "夏目響.jpg?t=1736620634",
      "MIKU.jpg": "MIKU.jpg?t=1736620634",
      "乃木絢愛.jpg": "乃木絢愛.jpg?t=1736620634",
      "滝川ソフィア.jpg": "滝川ソフィア.jpg?t=1736620634",
      "新川ゆず.jpg": "新川ゆず.jpg?t=1736620634",
      "愛花紗也.jpg": "愛花紗也.jpg?t=1736620634",
      "桜香美羽.jpg": "桜香美羽.jpg?t=1736620634",
      "与田知佳.jpg": "与田知佳.jpg?t=1736620634",
      "二葉エマ.jpg": "二葉エマ.jpg?t=1736620634",
      "牧野れいな.jpg": "牧野れいな.jpg?t=1736620634",
      "高瀬りな.jpg": "高瀬りな.jpg?t=1736620634",
      "流川夕.jpg": "流川夕.jpg?t=1736620634",
      "倉多まお.jpg": "倉多まお.jpg?t=1736620634",
      "Hitomi.jpg": "Hitomi.jpg?t=1736620634",
      "ゆうひ菜那.jpg": "ゆうひ菜那.jpg?t=1736620634",
      "大橋未久.jpg": "大橋未久.jpg?t=1736620634",
      "白杞りり.jpg": "白杞りり.jpg?t=1736620634",
      "松岡すず.jpg": "松岡すず.jpg?t=1736620634",
      "原紗央莉.jpg": "原紗央莉.jpg?t=1736620634",
      "ゆりえ.jpg": "ゆりえ.jpg?t=1736620634",
      "木村玲衣.jpg": "木村玲衣.jpg?t=1736620634",
      "桃谷エリカ.jpg": "桃谷エリカ.jpg?t=1736620634",
      "南真菜果.jpg": "南真菜果.jpg?t=1736620634",
      "明里つむぎ.jpg": "明里つむぎ.jpg?t=1736620634",
      "涼宮遙香.jpg": "涼宮遙香.jpg?t=1736620634",
      "桃乃木かな.jpg": "桃乃木かな.jpg?t=1736620634",
      "七ツ森りり.jpg": "七ツ森りり.jpg?t=1736620634",
      "天河みなせ.jpg": "天河みなせ.jpg?t=1736620634",
      "涩谷果步.jpg": "涩谷果步.jpg?t=1736620634",
      "高橋しょう子.jpg": "高橋しょう子.jpg?t=1736620634",
      "伊藤舞雪.jpg": "伊藤舞雪.jpg?t=1736620634",
      "明日花キララ.jpg": "明日花キララ.jpg?t=1736620634",
      "上原亜衣.jpg": "上原亜衣.jpg?t=1736620634",
      "蒼井そら.jpg": "蒼井そら.jpg?t=1736620634",
      "如月えれな.jpg": "如月えれな.jpg?t=1736620634",
      "☆LUNA☆.jpg": "☆LUNA☆.jpg?t=1736620634",
      "九条みちる.jpg": "九条みちる.jpg?t=1736620634",
      "潮美舞.jpg": "潮美舞.jpg?t=1736620634",
      "橘玛丽.jpg": "橘玛丽.jpg?t=1736620634",
      "市川つばさ.jpg": "市川つばさ.jpg?t=1736620634",
      "葵つかさ.jpg": "葵つかさ.jpg?t=1736620634",
      "美織.jpg": "美織.jpg?t=1736620634",
      "Rio.jpg": "Rio.jpg?t=1736620634",
      "岬ななみ.jpg": "岬ななみ.jpg?t=1736620634",
      "夢乃あいか.jpg": "夢乃あいか.jpg?t=1736620634",
      "斎藤あみり.jpg": "斎藤あみり.jpg?t=1736620634",
      "绪川凛.jpg": "绪川凛.jpg?t=1736620634",
      "楓ふうあ.jpg": "楓ふうあ.jpg?t=1736620634",
      "222.jpg": "222.jpg?t=1736620634",
      "林美玲.jpg": "林美玲.jpg?t=1736620634",
      "小宵こなん.jpg": "小宵こなん.jpg?t=1736620634",
      "山本蓮加.jpg": "山本蓮加.jpg?t=1736620634",
      "美ノ嶋 めぐり.jpg": "美ノ嶋 めぐり.jpg?t=1736620634",
      "しらいしゆい-1.jpg": "しらいしゆい-1.jpg?t=1736620634",
      "小岩いと.jpg": "小岩いと.jpg?t=1736620634",
      "石原希望.jpg": "石原希望.jpg?t=1736620634",
      "天野るみ.jpg": "天野るみ.jpg?t=1736620634",
      "和久井美兎.jpg": "和久井美兎.jpg?t=1736620634",
      "岸えま.jpg": "岸えま.jpg?t=1736620634",
      "梓ヒカリ.jpg": "梓ヒカリ.jpg?t=1736620634",
      "時田萌々.jpg": "時田萌々.jpg?t=1736620634",
      "夕雛エミリ.jpg": "夕雛エミリ.jpg?t=1736620634",
      "桃乃りん.jpg": "桃乃りん.jpg?t=1736620634",
      "水野朝陽.jpg": "水野朝陽.jpg?t=1736620634",
      "白咲かんな.jpg": "白咲かんな.jpg?t=1736620634",
      "西山希.jpg": "西山希.jpg?t=1736620634",
      "希美かんな.jpg": "希美かんな.jpg?t=1736620634",
      "楓彩.jpg": "楓彩.jpg?t=1736620634",
      "黒崎セシル.jpg": "黒崎セシル.jpg?t=1736620634",
      "宫城りえ.jpg": "宫城りえ.jpg?t=1736620634",
      "miru.jpg": "miru.jpg?t=1736620634",
      "花岡よし乃.jpg": "花岡よし乃.jpg?t=1736620634",
      "河北彩花.jpg": "河北彩花.jpg?t=1736620634",
      "宍戸里帆.jpg": "宍戸里帆.jpg?t=1736620634",
      "神谷凪.jpg": "神谷凪.jpg?t=1736620634",
      "吉沢明歩.jpg": "吉沢明歩.jpg?t=1736620634",
      "天音まひな.jpg": "天音まひな.jpg?t=1736620634",
      "桃咲ゆり菜.jpg": "桃咲ゆり菜.jpg?t=1736620634",
      "小鳩麦.jpg": "小鳩麦.jpg?t=1736620634",
      "如月结衣.jpg": "如月结衣.jpg?t=1736620634",
      "夢実かなえ.jpg": "夢実かなえ.jpg?t=1736620634",
      "はやのうた.jpg": "はやのうた.jpg?t=1736620634",
      "山吹らん.jpg": "山吹らん.jpg?t=1736620634",
      "篠田ゆう.jpg": "篠田ゆう.jpg?t=1736620634",
      "田中ねね.jpg": "田中ねね.jpg?t=1736620634",
      "時田萌々_p.jpg": "時田萌々_p.jpg?t=1736620634",
      "横宮七海.jpg": "横宮七海.jpg?t=1736620634",
      "皇ゆず.jpg": "皇ゆず.jpg?t=1736620634",
      "吉見奈央.jpg": "吉見奈央.jpg?t=1736620634",
      "古瀬玲.jpg": "古瀬玲.jpg?t=1736620634",
      "三上悠亜.jpg": "三上悠亜.jpg?t=1736620634",
      "二宮小夜子.jpg": "二宮小夜子.jpg?t=1736620634",
      "水咲ローラ.jpg": "水咲ローラ.jpg?t=1736620634",
      "岸田歩美.jpg": "岸田歩美.jpg?t=1736620634",
      "本真ゆり.jpg": "本真ゆり.jpg?t=1736620634",
      "桜羽のどか.jpg": "桜羽のどか.jpg?t=1736620634",
      "朝田ひまり.jpg": "朝田ひまり.jpg?t=1736620634",
      "水川スミレ.jpg": "水川スミレ.jpg?t=1736620634",
      "MINAMO.jpg": "MINAMO.jpg?t=1736620634",
      "メロディー・雛・マークス.jpg": "メロディー・雛・マークス.jpg?t=1736620634",
      "一乃あおい.jpg": "一乃あおい.jpg?t=1736620634",
      "しらいしゆい.jpg": "しらいしゆい.jpg?t=1736620634",
      "爱田奈々.jpg": "爱田奈々.jpg?t=1736620634",
      "北条麻妃.jpg": "北条麻妃.jpg?t=1736620634",
      "新谷未来.jpg": "新谷未来.jpg?t=1736620634",
      "七嶋舞.jpg": "七嶋舞.jpg?t=1736620634"
    }
  },
  "Information": {
    "TotalNum": 119,
    "TotalSize": 16990300,
    "Timestamp": 1736620690.689856
  }
}
